mcrp_cgam-0.2.0.dist-info/RECORD
mcrp_cgam-0.2.0.dist-info/WHEEL
mcrp_cgam-0.2.0.dist-info/METADATA
mcrp_cgam-0.2.0.dist-info/top_level.txt
mcrp_cgam-0.2.0.data/scripts/cgam
mcrp_cgam/main.so
mcrp_cgam/copt.so
mcrp_cgam/expand.so
mcrp_cgam/cells.so
mcrp_cgam/lhs.so
mcrp_cgam/scsurfaces.so
mcrp_cgam/transforms.so
mcrp_cgam/surfaces.so
mcrp_cgam/another_parser.so
mcrp_cgam/__init__.py
mcrp_cgam/mcnp2sc.so
