Metadata-Version: 2.1
Name: mcrp-cgam
Version: 0.2.0
Summary: MCNP-related packages. Cell geometry algebraic manipulation
Home-page: https://github.com/travleev/mcnp2spaceclaim
Author: A. Travleev
Author-email: anton.travleev@gmail.com
License: UNKNOWN
Keywords: MCNP geometry algebra
Platform: UNKNOWN
Provides: mcrp_cgam
Requires-Dist: numpy
Requires-Dist: scipy
Requires-Dist: mcrp-utils
Requires-Dist: mcrp-splitters
